py_poetry/__init__.py
py_poetry/main.py
py_poetry-0.1.1.dist-info/WHEEL
py_poetry-0.1.1.dist-info/METADATA
py_poetry-0.1.1.dist-info/RECORD
