Metadata-Version: 2.1
Name: py-poetry
Version: 0.1.1
Summary: LOL
Author: Qaminono
Author-email: 36382154+Qaminono@users.noreply.github.com
Requires-Python: >=3.9,<4.0
Classifier: Programming Language :: Python :: 3
Classifier: Programming Language :: Python :: 3.10
Classifier: Programming Language :: Python :: 3.9
Requires-Dist: Django (>=4.0.1,<5.0.0)
